classify.py
cmi_email.py
extract.py
helper.py
main.py
setup.py
cmi_extract_tool-1.0.dist-info/METADATA
cmi_extract_tool-1.0.dist-info/WHEEL
cmi_extract_tool-1.0.dist-info/top_level.txt
cmi_extract_tool-1.0.dist-info/RECORD
