Metadata-Version: 2.1
Name: cmi-extract-tool
Version: 1.0
Summary: cmi_extract_tool for oval tech
Home-page: https://git.pharm-hub.com.cn:8443/web-crawling/python
Author: Yuheng Wu
Author-email: wuyuheng@oval-tech.com
License: OVAL TECH
Requires: imaplib
Requires: imap_tools
Requires: pandas
